richerface/__init__.py
richerface/face.py
richerface-0.1.0.dist-info/METADATA
richerface-0.1.0.dist-info/WHEEL
richerface-0.1.0.dist-info/entry_points.txt
richerface-0.1.0.dist-info/top_level.txt
richerface-0.1.0.dist-info/RECORD
