Metadata-Version: 2.1
Name: richerface
Version: 0.1.0
Summary: A package for training and evaluating facial recognition models.
Author: Akshay
Author-email: your.email@example.com
Requires-Dist: tensorflow>=2.0
Requires-Dist: opencv-python
Requires-Dist: matplotlib
Requires-Dist: numpy
